{
    "Game": "2022-10-12T00:00:00",
    "Team": "Colorado Avalanche",
    "PK_TOI": 4.7,
    "PP_CF": 12.0,
    "PK_CA": 3.0,
    "PP_SF": 8.0,
    "PK_SA": 2.0,
    "PP_GF": 4.0,
    "PK_GA": 2.0,
    "PP_SHOOT_%": 50.0,
    "PK_SAVE_%": 0.0,
    "PP_OPP": 6,
    "PP%": 71.42857142857143,
    "PK%": 71.42857142857143,
    "players": [
        {
            "name": "Alex Newhook",
            "TOI": 1.8666666666667,
            "points": 0.0,
            "iCF": 0.0,
            "iSCF": 0.0,
            "iHDCF": 0.0
        },
        {
            "name": "Artturi Lehkonen",
            "TOI": 5.8833333333333,
            "points": 3.0,
            "iCF": 2.0,
            "iSCF": 2.0,
            "iHDCF": 2.0
        },
        {
            "name": "Bowen Byram",
            "TOI": 1.7333333333333,
            "points": 0.0,
            "iCF": 1.0,
            "iSCF": 0.0,
            "iHDCF": 0.0
        },
        {
            "name": "Cale Makar",
            "TOI": 5.6833333333333,
            "points": 2.0,
            "iCF": 1.0,
            "iSCF": 0.0,
            "iHDCF": 0.0
        },
        {
            "name": "Devon Toews",
            "TOI": 2.1666666666667,
            "points": 0.0,
            "iCF": 0.0,
            "iSCF": 0.0,
            "iHDCF": 0.0
        },
        {
            "name": "Evan Rodrigues",
            "TOI": 1.85,
            "points": 0.0,
            "iCF": 0.0,
            "iSCF": 0.0,
            "iHDCF": 0.0
        },
        {
            "name": "Mikko Rantanen",
            "TOI": 5.9833333333333,
            "points": 4.0,
            "iCF": 1.0,
            "iSCF": 0.0,
            "iHDCF": 0.0
        },
        {
            "name": "Nathan MacKinnon",
            "TOI": 5.95,
            "points": 1.0,
            "iCF": 4.0,
            "iSCF": 1.0,
            "iHDCF": 0.0
        },
        {
            "name": "Samuel Girard",
            "TOI": 1.8333333333333,
            "points": 0.0,
            "iCF": 0.0,
            "iSCF": 0.0,
            "iHDCF": 0.0
        },
        {
            "name": "Valeri Nichushkin",
            "TOI": 5.8833333333333,
            "points": 2.0,
            "iCF": 3.0,
            "iSCF": 3.0,
            "iHDCF": 3.0
        }
    ]
}