{
    "Game": "2023-10-22T00:00:00",
    "Team": "Boston Bruins",
    "PK_TOI": 5.3,
    "PP_CF": 20.0,
    "PK_CA": 10.0,
    "PP_SF": 10.0,
    "PK_SA": 5.0,
    "PP_GF": 0.0,
    "PK_GA": 0.0,
    "PP_SHOOT_%": 0.0,
    "PK_SAVE_%": 100.0,
    "PP_OPP": 5,
    "PP%": 16.666666666666664,
    "PK%": 100.0,
    "players": [
        {
            "name": "Brad Marchand",
            "TOI": 6.9666666666667,
            "points": 0.0,
            "iCF": 0.0,
            "iSCF": 0.0,
            "iHDCF": 0.0
        },
        {
            "name": "Charlie McAvoy",
            "TOI": 6.95,
            "points": 0.0,
            "iCF": 3.0,
            "iSCF": 2.0,
            "iHDCF": 0.0
        },
        {
            "name": "David Pastrnak",
            "TOI": 6.9666666666667,
            "points": 0.0,
            "iCF": 7.0,
            "iSCF": 4.0,
            "iHDCF": 0.0
        },
        {
            "name": "Hampus Lindholm",
            "TOI": 1.35,
            "points": 0.0,
            "iCF": 1.0,
            "iSCF": 0.0,
            "iHDCF": 0.0
        },
        {
            "name": "Ian Mitchell",
            "TOI": 0.15,
            "points": 0.0,
            "iCF": 0.0,
            "iSCF": 0.0,
            "iHDCF": 0.0
        },
        {
            "name": "Jake DeBrusk",
            "TOI": 1.35,
            "points": 0.0,
            "iCF": 0.0,
            "iSCF": 0.0,
            "iHDCF": 0.0
        },
        {
            "name": "James van Riemsdyk",
            "TOI": 6.7166666666667,
            "points": 0.0,
            "iCF": 4.0,
            "iSCF": 3.0,
            "iHDCF": 3.0
        },
        {
            "name": "Kevin Shattenkirk",
            "TOI": 1.3666666666667,
            "points": 0.0,
            "iCF": 0.0,
            "iSCF": 0.0,
            "iHDCF": 0.0
        },
        {
            "name": "Matthew Poitras",
            "TOI": 1.3666666666667,
            "points": 0.0,
            "iCF": 2.0,
            "iSCF": 1.0,
            "iHDCF": 0.0
        },
        {
            "name": "Morgan Geekie",
            "TOI": 1.45,
            "points": 0.0,
            "iCF": 0.0,
            "iSCF": 0.0,
            "iHDCF": 0.0
        },
        {
            "name": "Pavel Zacha",
            "TOI": 6.95,
            "points": 0.0,
            "iCF": 3.0,
            "iSCF": 1.0,
            "iHDCF": 0.0
        }
    ]
}