{
    "Game": "2023-04-08T00:00:00",
    "Team": "Montreal Canadiens",
    "PK_TOI": 7.583333333333333,
    "PP_CF": 7.0,
    "PK_CA": 15.0,
    "PP_SF": 3.0,
    "PK_SA": 6.0,
    "PP_GF": 0.0,
    "PK_GA": 4.0,
    "PP_SHOOT_%": 0.0,
    "PK_SAVE_%": 33.33,
    "PP_OPP": 4,
    "PP%": 20.0,
    "PK%": 20.0,
    "players": [
        {
            "name": "Brendan Gallagher",
            "TOI": 2.4,
            "points": 0.0,
            "iCF": 2.0,
            "iSCF": 2.0,
            "iHDCF": 1.0
        },
        {
            "name": "Chris Wideman",
            "TOI": 1.6,
            "points": 0.0,
            "iCF": 1.0,
            "iSCF": 0.0,
            "iHDCF": 0.0
        },
        {
            "name": "Denis Gurianov",
            "TOI": 2.2833333333333,
            "points": 0.0,
            "iCF": 0.0,
            "iSCF": 0.0,
            "iHDCF": 0.0
        },
        {
            "name": "Jake Evans",
            "TOI": 0.1,
            "points": 0.0,
            "iCF": 0.0,
            "iSCF": 0.0,
            "iHDCF": 0.0
        },
        {
            "name": "Jesse Ylonen",
            "TOI": 0.1,
            "points": 0.0,
            "iCF": 0.0,
            "iSCF": 0.0,
            "iHDCF": 0.0
        },
        {
            "name": "Joel Armia",
            "TOI": 5.5,
            "points": 0.0,
            "iCF": 0.0,
            "iSCF": 0.0,
            "iHDCF": 0.0
        },
        {
            "name": "Johnathan Kovacevic",
            "TOI": 0.083333333333333,
            "points": 0.0,
            "iCF": 0.0,
            "iSCF": 0.0,
            "iHDCF": 0.0
        },
        {
            "name": "Jonathan Drouin",
            "TOI": 2.3833333333333,
            "points": 0.0,
            "iCF": 0.0,
            "iSCF": 0.0,
            "iHDCF": 0.0
        },
        {
            "name": "Justin Barron",
            "TOI": 0.55,
            "points": 0.0,
            "iCF": 0.0,
            "iSCF": 0.0,
            "iHDCF": 0.0
        },
        {
            "name": "Michael Pezzetta",
            "TOI": 0.083333333333333,
            "points": 0.0,
            "iCF": 0.0,
            "iSCF": 0.0,
            "iHDCF": 0.0
        },
        {
            "name": "Mike Hoffman",
            "TOI": 5.6166666666667,
            "points": 0.0,
            "iCF": 1.0,
            "iSCF": 0.0,
            "iHDCF": 0.0
        },
        {
            "name": "Mike Matheson",
            "TOI": 5.85,
            "points": 0.0,
            "iCF": 2.0,
            "iSCF": 0.0,
            "iHDCF": 0.0
        },
        {
            "name": "Nick Suzuki",
            "TOI": 5.55,
            "points": 0.0,
            "iCF": 1.0,
            "iSCF": 1.0,
            "iHDCF": 0.0
        },
        {
            "name": "Rafael Harvey-Pinard",
            "TOI": 5.4333333333333,
            "points": 0.0,
            "iCF": 0.0,
            "iSCF": 0.0,
            "iHDCF": 0.0
        },
        {
            "name": "Rem Pitlick",
            "TOI": 2.4666666666667,
            "points": 0.0,
            "iCF": 0.0,
            "iSCF": 0.0,
            "iHDCF": 0.0
        }
    ]
}