{
    "Game": "2023-04-04T00:00:00",
    "Team": "Vancouver Canucks",
    "PK_TOI": 6.683333333333334,
    "PP_CF": 15.0,
    "PK_CA": 10.0,
    "PP_SF": 5.0,
    "PK_SA": 4.0,
    "PP_GF": 0.0,
    "PK_GA": 1.0,
    "PP_SHOOT_%": 0.0,
    "PK_SAVE_%": 75.0,
    "PP_OPP": 6,
    "PP%": 14.285714285714285,
    "PK%": 85.71428571428571,
    "players": [
        {
            "name": "Aidan McDonough",
            "TOI": 0.73333333333333,
            "points": 0.0,
            "iCF": 0.0,
            "iSCF": 0.0,
            "iHDCF": 0.0
        },
        {
            "name": "Akito Hirose",
            "TOI": 2.25,
            "points": 0.0,
            "iCF": 0.0,
            "iSCF": 0.0,
            "iHDCF": 0.0
        },
        {
            "name": "Andrei Kuzmenko",
            "TOI": 4.85,
            "points": 0.0,
            "iCF": 3.0,
            "iSCF": 3.0,
            "iHDCF": 2.0
        },
        {
            "name": "Anthony Beauvillier",
            "TOI": 2.55,
            "points": 0.0,
            "iCF": 0.0,
            "iSCF": 0.0,
            "iHDCF": 0.0
        },
        {
            "name": "Brock Boeser",
            "TOI": 4.8166666666667,
            "points": 0.0,
            "iCF": 4.0,
            "iSCF": 4.0,
            "iHDCF": 2.0
        },
        {
            "name": "Conor Garland",
            "TOI": 2.5333333333333,
            "points": 0.0,
            "iCF": 2.0,
            "iSCF": 1.0,
            "iHDCF": 0.0
        },
        {
            "name": "Elias Pettersson",
            "TOI": 4.75,
            "points": 0.0,
            "iCF": 1.0,
            "iSCF": 1.0,
            "iHDCF": 1.0
        },
        {
            "name": "Ethan Bear",
            "TOI": 0.033333333333333,
            "points": 0.0,
            "iCF": 0.0,
            "iSCF": 0.0,
            "iHDCF": 0.0
        },
        {
            "name": "J.T. Miller",
            "TOI": 5.35,
            "points": 0.0,
            "iCF": 0.0,
            "iSCF": 0.0,
            "iHDCF": 0.0
        },
        {
            "name": "Jack Rathbone",
            "TOI": 1.4666666666667,
            "points": 0.0,
            "iCF": 1.0,
            "iSCF": 1.0,
            "iHDCF": 0.0
        },
        {
            "name": "Jack Studnicka",
            "TOI": 0.76666666666667,
            "points": 0.0,
            "iCF": 0.0,
            "iSCF": 0.0,
            "iHDCF": 0.0
        },
        {
            "name": "Kyle Burroughs",
            "TOI": 0.73333333333333,
            "points": 0.0,
            "iCF": 0.0,
            "iSCF": 0.0,
            "iHDCF": 0.0
        },
        {
            "name": "Nils Aman",
            "TOI": 0.016666666666667,
            "points": 0.0,
            "iCF": 0.0,
            "iSCF": 0.0,
            "iHDCF": 0.0
        },
        {
            "name": "Phillip Di Giuseppe",
            "TOI": 0.05,
            "points": 0.0,
            "iCF": 0.0,
            "iSCF": 0.0,
            "iHDCF": 0.0
        },
        {
            "name": "Quinn Hughes",
            "TOI": 6.0166666666667,
            "points": 0.0,
            "iCF": 1.0,
            "iSCF": 1.0,
            "iHDCF": 0.0
        },
        {
            "name": "Sheldon Dries",
            "TOI": 2.25,
            "points": 0.0,
            "iCF": 0.0,
            "iSCF": 0.0,
            "iHDCF": 0.0
        },
        {
            "name": "Tyler Myers",
            "TOI": 0.91666666666667,
            "points": 0.0,
            "iCF": 1.0,
            "iSCF": 0.0,
            "iHDCF": 0.0
        }
    ]
}