{
    "Game": "2023-10-13T00:00:00",
    "Team": "Washington Capitals",
    "PK_TOI": 3.1666666666666665,
    "PP_CF": 10.0,
    "PK_CA": 9.0,
    "PP_SF": 1.0,
    "PK_SA": 5.0,
    "PP_GF": 0.0,
    "PK_GA": 2.0,
    "PP_SHOOT_%": 0.0,
    "PK_SAVE_%": 60.0,
    "PP_OPP": 3,
    "PP%": 0.0,
    "PK%": 33.33333333333333,
    "players": [
        {
            "name": "Alex Ovechkin",
            "TOI": 5.35,
            "points": 0.0,
            "iCF": 3.0,
            "iSCF": 1.0,
            "iHDCF": 0.0
        },
        {
            "name": "Anthony Mantha",
            "TOI": 1.8,
            "points": 0.0,
            "iCF": 1.0,
            "iSCF": 0.0,
            "iHDCF": 0.0
        },
        {
            "name": "Connor McMichael",
            "TOI": 0.033333333333333,
            "points": 0.0,
            "iCF": 0.0,
            "iSCF": 0.0,
            "iHDCF": 0.0
        },
        {
            "name": "Dylan Strome",
            "TOI": 1.6,
            "points": 0.0,
            "iCF": 1.0,
            "iSCF": 1.0,
            "iHDCF": 0.0
        },
        {
            "name": "Evgeny Kuznetsov",
            "TOI": 3.75,
            "points": 0.0,
            "iCF": 1.0,
            "iSCF": 0.0,
            "iHDCF": 0.0
        },
        {
            "name": "John Carlson",
            "TOI": 3.7,
            "points": 0.0,
            "iCF": 1.0,
            "iSCF": 0.0,
            "iHDCF": 0.0
        },
        {
            "name": "Matthew Phillips",
            "TOI": 0.033333333333333,
            "points": 0.0,
            "iCF": 0.0,
            "iSCF": 0.0,
            "iHDCF": 0.0
        },
        {
            "name": "Nic Dowd",
            "TOI": 0.033333333333333,
            "points": 0.0,
            "iCF": 0.0,
            "iSCF": 0.0,
            "iHDCF": 0.0
        },
        {
            "name": "Nick Jensen",
            "TOI": 0.033333333333333,
            "points": 0.0,
            "iCF": 0.0,
            "iSCF": 0.0,
            "iHDCF": 0.0
        },
        {
            "name": "Nicklas Backstrom",
            "TOI": 3.55,
            "points": 0.0,
            "iCF": 0.0,
            "iSCF": 0.0,
            "iHDCF": 0.0
        },
        {
            "name": "Rasmus Sandin",
            "TOI": 1.6833333333333,
            "points": 0.0,
            "iCF": 1.0,
            "iSCF": 0.0,
            "iHDCF": 0.0
        },
        {
            "name": "T.J. Oshie",
            "TOI": 3.3166666666667,
            "points": 0.0,
            "iCF": 1.0,
            "iSCF": 1.0,
            "iHDCF": 1.0
        },
        {
            "name": "Tom Wilson",
            "TOI": 2.0333333333333,
            "points": 0.0,
            "iCF": 1.0,
            "iSCF": 1.0,
            "iHDCF": 0.0
        }
    ]
}