{
    "Game": "2022-10-29T00:00:00",
    "Team": "Washington Capitals",
    "PK_TOI": 10.0,
    "PP_CF": 10.0,
    "PK_CA": 21.0,
    "PP_SF": 6.0,
    "PK_SA": 8.0,
    "PP_GF": 0.0,
    "PK_GA": 0.0,
    "PP_SHOOT_%": 0.0,
    "PK_SAVE_%": 100.0,
    "PP_OPP": 3,
    "PP%": 25.0,
    "PK%": 100.0,
    "players": [
        {
            "name": "Alex Ovechkin",
            "TOI": 5.9333333333333,
            "points": 0.0,
            "iCF": 2.0,
            "iSCF": 1.0,
            "iHDCF": 0.0
        },
        {
            "name": "Aliaksei Protas",
            "TOI": 1.5,
            "points": 0.0,
            "iCF": 0.0,
            "iSCF": 0.0,
            "iHDCF": 0.0
        },
        {
            "name": "Anthony Mantha",
            "TOI": 0.91666666666667,
            "points": 0.0,
            "iCF": 1.0,
            "iSCF": 0.0,
            "iHDCF": 0.0
        },
        {
            "name": "Beck Malenstyn",
            "TOI": 0.05,
            "points": 0.0,
            "iCF": 0.0,
            "iSCF": 0.0,
            "iHDCF": 0.0
        },
        {
            "name": "Conor Sheary",
            "TOI": 1.7833333333333,
            "points": 0.0,
            "iCF": 1.0,
            "iSCF": 1.0,
            "iHDCF": 1.0
        },
        {
            "name": "Dmitry Orlov",
            "TOI": 3.5666666666667,
            "points": 0.0,
            "iCF": 1.0,
            "iSCF": 0.0,
            "iHDCF": 0.0
        },
        {
            "name": "Dylan Strome",
            "TOI": 4.2666666666667,
            "points": 0.0,
            "iCF": 0.0,
            "iSCF": 0.0,
            "iHDCF": 0.0
        },
        {
            "name": "Erik Gustafsson",
            "TOI": 1.2833333333333,
            "points": 0.0,
            "iCF": 1.0,
            "iSCF": 0.0,
            "iHDCF": 0.0
        },
        {
            "name": "Evgeny Kuznetsov",
            "TOI": 3.7833333333333,
            "points": 0.0,
            "iCF": 3.0,
            "iSCF": 1.0,
            "iHDCF": 1.0
        },
        {
            "name": "Garnet Hathaway",
            "TOI": 0.05,
            "points": 0.0,
            "iCF": 0.0,
            "iSCF": 0.0,
            "iHDCF": 0.0
        },
        {
            "name": "John Carlson",
            "TOI": 1.1,
            "points": 0.0,
            "iCF": 0.0,
            "iSCF": 0.0,
            "iHDCF": 0.0
        },
        {
            "name": "Marcus Johansson",
            "TOI": 4.45,
            "points": 0.0,
            "iCF": 1.0,
            "iSCF": 1.0,
            "iHDCF": 1.0
        },
        {
            "name": "Martin Fehervary",
            "TOI": 0.083333333333333,
            "points": 0.0,
            "iCF": 0.0,
            "iSCF": 0.0,
            "iHDCF": 0.0
        },
        {
            "name": "Nic Dowd",
            "TOI": 0.05,
            "points": 0.0,
            "iCF": 0.0,
            "iSCF": 0.0,
            "iHDCF": 0.0
        },
        {
            "name": "Nick Jensen",
            "TOI": 0.1,
            "points": 0.0,
            "iCF": 0.0,
            "iSCF": 0.0,
            "iHDCF": 0.0
        },
        {
            "name": "T.J. Oshie",
            "TOI": 1.0833333333333,
            "points": 0.0,
            "iCF": 0.0,
            "iSCF": 0.0,
            "iHDCF": 0.0
        }
    ]
}