{
    "Game": "2023-02-11T00:00:00",
    "Team": "Calgary Flames",
    "PK_TOI": 5.283333333333333,
    "PP_CF": 5.0,
    "PK_CA": 14.0,
    "PP_SF": 4.0,
    "PK_SA": 6.0,
    "PP_GF": 1.0,
    "PK_GA": 1.0,
    "PP_SHOOT_%": 25.0,
    "PK_SAVE_%": 83.33,
    "PP_OPP": 3,
    "PP%": 50.0,
    "PK%": 75.0,
    "players": [
        {
            "name": "Andrew Mangiapane",
            "TOI": 2.9166666666667,
            "points": 0.0,
            "iCF": 1.0,
            "iSCF": 1.0,
            "iHDCF": 0.0
        },
        {
            "name": "Chris Tanev",
            "TOI": 0.25,
            "points": 0.0,
            "iCF": 0.0,
            "iSCF": 0.0,
            "iHDCF": 0.0
        },
        {
            "name": "Dillon Dube",
            "TOI": 3.0333333333333,
            "points": 1.0,
            "iCF": 0.0,
            "iSCF": 0.0,
            "iHDCF": 0.0
        },
        {
            "name": "Elias Lindholm",
            "TOI": 2.9,
            "points": 0.0,
            "iCF": 0.0,
            "iSCF": 0.0,
            "iHDCF": 0.0
        },
        {
            "name": "Jakob Pelletier",
            "TOI": 2.45,
            "points": 0.0,
            "iCF": 1.0,
            "iSCF": 1.0,
            "iHDCF": 0.0
        },
        {
            "name": "Jonathan Huberdeau",
            "TOI": 2.7,
            "points": 0.0,
            "iCF": 0.0,
            "iSCF": 0.0,
            "iHDCF": 0.0
        },
        {
            "name": "MacKenzie Weegar",
            "TOI": 3.3,
            "points": 0.0,
            "iCF": 0.0,
            "iSCF": 0.0,
            "iHDCF": 0.0
        },
        {
            "name": "Mikael Backlund",
            "TOI": 3.15,
            "points": 0.0,
            "iCF": 0.0,
            "iSCF": 0.0,
            "iHDCF": 0.0
        },
        {
            "name": "Milan Lucic",
            "TOI": 0.083333333333333,
            "points": 0.0,
            "iCF": 0.0,
            "iSCF": 0.0,
            "iHDCF": 0.0
        },
        {
            "name": "Nazem Kadri",
            "TOI": 2.8333333333333,
            "points": 0.0,
            "iCF": 0.0,
            "iSCF": 0.0,
            "iHDCF": 0.0
        },
        {
            "name": "Nikita Zadorov",
            "TOI": 0.18333333333333,
            "points": 0.0,
            "iCF": 0.0,
            "iSCF": 0.0,
            "iHDCF": 0.0
        },
        {
            "name": "Noah Hanifin",
            "TOI": 2.5666666666667,
            "points": 0.0,
            "iCF": 2.0,
            "iSCF": 0.0,
            "iHDCF": 0.0
        },
        {
            "name": "Trevor Lewis",
            "TOI": 0.15,
            "points": 0.0,
            "iCF": 0.0,
            "iSCF": 0.0,
            "iHDCF": 0.0
        },
        {
            "name": "Tyler Toffoli",
            "TOI": 2.9833333333333,
            "points": 1.0,
            "iCF": 1.0,
            "iSCF": 0.0,
            "iHDCF": 0.0
        }
    ]
}