{
    "Game": "2022-11-11T00:00:00",
    "Team": "Toronto Maple Leafs",
    "PK_TOI": 2.0,
    "PP_CF": 16.0,
    "PK_CA": 3.0,
    "PP_SF": 9.0,
    "PK_SA": 2.0,
    "PP_GF": 1.0,
    "PK_GA": 0.0,
    "PP_SHOOT_%": 11.11,
    "PK_SAVE_%": 100.0,
    "PP_OPP": 3,
    "PP%": 50.0,
    "PK%": 100.0,
    "players": [
        {
            "name": "Alexander Kerfoot",
            "TOI": 1.1666666666667,
            "points": 0.0,
            "iCF": 0.0,
            "iSCF": 0.0,
            "iHDCF": 0.0
        },
        {
            "name": "Auston Matthews",
            "TOI": 4.05,
            "points": 0.0,
            "iCF": 4.0,
            "iSCF": 3.0,
            "iHDCF": 1.0
        },
        {
            "name": "Calle Jarnkrok",
            "TOI": 0.58333333333333,
            "points": 0.0,
            "iCF": 0.0,
            "iSCF": 0.0,
            "iHDCF": 0.0
        },
        {
            "name": "David Kampf",
            "TOI": 0.51666666666667,
            "points": 0.0,
            "iCF": 1.0,
            "iSCF": 0.0,
            "iHDCF": 0.0
        },
        {
            "name": "Denis Malgin",
            "TOI": 1.2166666666667,
            "points": 0.0,
            "iCF": 0.0,
            "iSCF": 0.0,
            "iHDCF": 0.0
        },
        {
            "name": "John Tavares",
            "TOI": 4.1833333333333,
            "points": 0.0,
            "iCF": 1.0,
            "iSCF": 0.0,
            "iHDCF": 0.0
        },
        {
            "name": "Justin Holl",
            "TOI": 0.05,
            "points": 0.0,
            "iCF": 0.0,
            "iSCF": 0.0,
            "iHDCF": 0.0
        },
        {
            "name": "Mark Giordano",
            "TOI": 0.7,
            "points": 0.0,
            "iCF": 1.0,
            "iSCF": 0.0,
            "iHDCF": 0.0
        },
        {
            "name": "Michael Bunting",
            "TOI": 1.7833333333333,
            "points": 0.0,
            "iCF": 0.0,
            "iSCF": 0.0,
            "iHDCF": 0.0
        },
        {
            "name": "Mitchell Marner",
            "TOI": 4.0666666666667,
            "points": 1.0,
            "iCF": 1.0,
            "iSCF": 0.0,
            "iHDCF": 0.0
        },
        {
            "name": "Morgan Rielly",
            "TOI": 4.05,
            "points": 1.0,
            "iCF": 2.0,
            "iSCF": 0.0,
            "iHDCF": 0.0
        },
        {
            "name": "Nicholas Robertson",
            "TOI": 1.1,
            "points": 0.0,
            "iCF": 1.0,
            "iSCF": 1.0,
            "iHDCF": 0.0
        },
        {
            "name": "Pierre Engvall",
            "TOI": 0.18333333333333,
            "points": 0.0,
            "iCF": 0.0,
            "iSCF": 0.0,
            "iHDCF": 0.0
        },
        {
            "name": "Rasmus Sandin",
            "TOI": 1.5666666666667,
            "points": 0.0,
            "iCF": 0.0,
            "iSCF": 0.0,
            "iHDCF": 0.0
        },
        {
            "name": "Timothy Liljegren",
            "TOI": 0.31666666666667,
            "points": 0.0,
            "iCF": 0.0,
            "iSCF": 0.0,
            "iHDCF": 0.0
        },
        {
            "name": "TJ Brodie",
            "TOI": 0.05,
            "points": 0.0,
            "iCF": 0.0,
            "iSCF": 0.0,
            "iHDCF": 0.0
        },
        {
            "name": "William Nylander",
            "TOI": 4.2,
            "points": 1.0,
            "iCF": 5.0,
            "iSCF": 2.0,
            "iHDCF": 2.0
        },
        {
            "name": "Zach Aston-Reese",
            "TOI": 0.05,
            "points": 0.0,
            "iCF": 0.0,
            "iSCF": 0.0,
            "iHDCF": 0.0
        }
    ]
}