{
    "Game": "2023-10-14T00:00:00",
    "Team": "Toronto Maple Leafs",
    "PK_TOI": 2.0,
    "PP_CF": 9.0,
    "PK_CA": 6.0,
    "PP_SF": 4.0,
    "PK_SA": 2.0,
    "PP_GF": 2.0,
    "PK_GA": 0.0,
    "PP_SHOOT_%": 50.0,
    "PK_SAVE_%": 100.0,
    "PP_OPP": 3,
    "PP%": 75.0,
    "PK%": 100.0,
    "players": [
        {
            "name": "Auston Matthews",
            "TOI": 2.8166666666667,
            "points": 0.0,
            "iCF": 1.0,
            "iSCF": 1.0,
            "iHDCF": 0.0
        },
        {
            "name": "Calle Jarnkrok",
            "TOI": 0.88333333333333,
            "points": 1.0,
            "iCF": 0.0,
            "iSCF": 0.0,
            "iHDCF": 0.0
        },
        {
            "name": "David Kampf",
            "TOI": 0.05,
            "points": 0.0,
            "iCF": 0.0,
            "iSCF": 0.0,
            "iHDCF": 0.0
        },
        {
            "name": "John Klingberg",
            "TOI": 2.9166666666667,
            "points": 0.0,
            "iCF": 1.0,
            "iSCF": 1.0,
            "iHDCF": 0.0
        },
        {
            "name": "John Tavares",
            "TOI": 2.8333333333333,
            "points": 0.0,
            "iCF": 2.0,
            "iSCF": 1.0,
            "iHDCF": 0.0
        },
        {
            "name": "Matthew Knies",
            "TOI": 0.033333333333333,
            "points": 0.0,
            "iCF": 0.0,
            "iSCF": 0.0,
            "iHDCF": 0.0
        },
        {
            "name": "Max Domi",
            "TOI": 0.88333333333333,
            "points": 0.0,
            "iCF": 0.0,
            "iSCF": 0.0,
            "iHDCF": 0.0
        },
        {
            "name": "Mitchell Marner",
            "TOI": 2.85,
            "points": 0.0,
            "iCF": 0.0,
            "iSCF": 0.0,
            "iHDCF": 0.0
        },
        {
            "name": "Morgan Rielly",
            "TOI": 0.81666666666667,
            "points": 1.0,
            "iCF": 0.0,
            "iSCF": 0.0,
            "iHDCF": 0.0
        },
        {
            "name": "Timothy Liljegren",
            "TOI": 0.88333333333333,
            "points": 0.0,
            "iCF": 0.0,
            "iSCF": 0.0,
            "iHDCF": 0.0
        },
        {
            "name": "TJ Brodie",
            "TOI": 0.05,
            "points": 0.0,
            "iCF": 0.0,
            "iSCF": 0.0,
            "iHDCF": 0.0
        },
        {
            "name": "Tyler Bertuzzi",
            "TOI": 0.85,
            "points": 1.0,
            "iCF": 2.0,
            "iSCF": 2.0,
            "iHDCF": 1.0
        },
        {
            "name": "William Nylander",
            "TOI": 2.8,
            "points": 0.0,
            "iCF": 2.0,
            "iSCF": 1.0,
            "iHDCF": 0.0
        }
    ]
}