{
    "Game": "2022-12-15T00:00:00",
    "Team": "New York Rangers",
    "PK_TOI": 5.983333333333333,
    "PP_CF": 5.0,
    "PK_CA": 5.0,
    "PP_SF": 3.0,
    "PK_SA": 4.0,
    "PP_GF": 1.0,
    "PK_GA": 0.0,
    "PP_SHOOT_%": 33.33,
    "PK_SAVE_%": 100.0,
    "PP_OPP": 1,
    "PP%": 100.0,
    "PK%": 100.0,
    "players": [
        {
            "name": "Adam Fox",
            "TOI": 1.0333333333333,
            "points": 0.0,
            "iCF": 2.0,
            "iSCF": 0.0,
            "iHDCF": 0.0
        },
        {
            "name": "Alexis Lafrenie\u0300re",
            "TOI": 0.45,
            "points": 1.0,
            "iCF": 0.0,
            "iSCF": 0.0,
            "iHDCF": 0.0
        },
        {
            "name": "Artemi Panarin",
            "TOI": 1.0333333333333,
            "points": 0.0,
            "iCF": 0.0,
            "iSCF": 0.0,
            "iHDCF": 0.0
        },
        {
            "name": "Chris Kreider",
            "TOI": 1.0333333333333,
            "points": 0.0,
            "iCF": 0.0,
            "iSCF": 0.0,
            "iHDCF": 0.0
        },
        {
            "name": "Filip Chytil",
            "TOI": 0.45,
            "points": 1.0,
            "iCF": 1.0,
            "iSCF": 0.0,
            "iHDCF": 0.0
        },
        {
            "name": "Jacob Trouba",
            "TOI": 0.45,
            "points": 0.0,
            "iCF": 0.0,
            "iSCF": 0.0,
            "iHDCF": 0.0
        },
        {
            "name": "Kaapo Kakko",
            "TOI": 0.45,
            "points": 1.0,
            "iCF": 1.0,
            "iSCF": 0.0,
            "iHDCF": 0.0
        },
        {
            "name": "Mika Zibanejad",
            "TOI": 1.0333333333333,
            "points": 0.0,
            "iCF": 1.0,
            "iSCF": 1.0,
            "iHDCF": 0.0
        },
        {
            "name": "Vincent Trocheck",
            "TOI": 1.0333333333333,
            "points": 0.0,
            "iCF": 0.0,
            "iSCF": 0.0,
            "iHDCF": 0.0
        },
        {
            "name": "Vitali Kravtsov",
            "TOI": 0.45,
            "points": 0.0,
            "iCF": 0.0,
            "iSCF": 0.0,
            "iHDCF": 0.0
        }
    ]
}