{
    "Game": "2023-01-13T00:00:00",
    "Team": "San Jose Sharks",
    "PK_TOI": 4.8,
    "PP_CF": 13.0,
    "PK_CA": 11.0,
    "PP_SF": 7.0,
    "PK_SA": 9.0,
    "PP_GF": 0.0,
    "PK_GA": 2.0,
    "PP_SHOOT_%": 0.0,
    "PK_SAVE_%": 77.78,
    "PP_OPP": 4,
    "PP%": 20.0,
    "PK%": 60.0,
    "players": [
        {
            "name": "Alexander Barabanov",
            "TOI": 2.9166666666667,
            "points": 0.0,
            "iCF": 0.0,
            "iSCF": 0.0,
            "iHDCF": 0.0
        },
        {
            "name": "Erik Karlsson",
            "TOI": 5.3666666666667,
            "points": 0.0,
            "iCF": 2.0,
            "iSCF": 0.0,
            "iHDCF": 0.0
        },
        {
            "name": "Jaycob Megna",
            "TOI": 0.016666666666667,
            "points": 0.0,
            "iCF": 0.0,
            "iSCF": 0.0,
            "iHDCF": 0.0
        },
        {
            "name": "Jonah Gadjovich",
            "TOI": 0.033333333333333,
            "points": 0.0,
            "iCF": 0.0,
            "iSCF": 0.0,
            "iHDCF": 0.0
        },
        {
            "name": "Kevin Labanc",
            "TOI": 2.6333333333333,
            "points": 0.0,
            "iCF": 3.0,
            "iSCF": 1.0,
            "iHDCF": 0.0
        },
        {
            "name": "Logan Couture",
            "TOI": 4.6333333333333,
            "points": 0.0,
            "iCF": 2.0,
            "iSCF": 0.0,
            "iHDCF": 0.0
        },
        {
            "name": "Marc-Edouard Vlasic",
            "TOI": 0.11666666666667,
            "points": 0.0,
            "iCF": 0.0,
            "iSCF": 0.0,
            "iHDCF": 0.0
        },
        {
            "name": "Mario Ferraro",
            "TOI": 0.56666666666667,
            "points": 0.0,
            "iCF": 0.0,
            "iSCF": 0.0,
            "iHDCF": 0.0
        },
        {
            "name": "Matt Nieto",
            "TOI": 2.2833333333333,
            "points": 0.0,
            "iCF": 1.0,
            "iSCF": 0.0,
            "iHDCF": 0.0
        },
        {
            "name": "Matthew Benning",
            "TOI": 2.15,
            "points": 0.0,
            "iCF": 0.0,
            "iSCF": 0.0,
            "iHDCF": 0.0
        },
        {
            "name": "Michael Eyssimont",
            "TOI": 1.0666666666667,
            "points": 0.0,
            "iCF": 1.0,
            "iSCF": 0.0,
            "iHDCF": 0.0
        },
        {
            "name": "Nick Bonino",
            "TOI": 3.3,
            "points": 0.0,
            "iCF": 2.0,
            "iSCF": 2.0,
            "iHDCF": 1.0
        },
        {
            "name": "Nico Sturm",
            "TOI": 2.65,
            "points": 0.0,
            "iCF": 0.0,
            "iSCF": 0.0,
            "iHDCF": 0.0
        },
        {
            "name": "Oskar Lindblom",
            "TOI": 0.18333333333333,
            "points": 0.0,
            "iCF": 0.0,
            "iSCF": 0.0,
            "iHDCF": 0.0
        },
        {
            "name": "Steven Lorentz",
            "TOI": 0.36666666666667,
            "points": 0.0,
            "iCF": 0.0,
            "iSCF": 0.0,
            "iHDCF": 0.0
        },
        {
            "name": "Timo Meier",
            "TOI": 4.8,
            "points": 0.0,
            "iCF": 1.0,
            "iSCF": 0.0,
            "iHDCF": 0.0
        },
        {
            "name": "Tomas Hertl",
            "TOI": 4.6666666666667,
            "points": 0.0,
            "iCF": 1.0,
            "iSCF": 1.0,
            "iHDCF": 1.0
        }
    ]
}