{
    "Game": "2023-01-21T00:00:00",
    "Team": "Dallas Stars",
    "PK_TOI": 6.0,
    "PP_CF": 16.0,
    "PK_CA": 6.0,
    "PP_SF": 10.0,
    "PK_SA": 5.0,
    "PP_GF": 1.0,
    "PK_GA": 0.0,
    "PP_SHOOT_%": 10.0,
    "PK_SAVE_%": 100.0,
    "PP_OPP": 4,
    "PP%": 40.0,
    "PK%": 100.0,
    "players": [
        {
            "name": "Colin Miller",
            "TOI": 2.05,
            "points": 0.0,
            "iCF": 2.0,
            "iSCF": 1.0,
            "iHDCF": 0.0
        },
        {
            "name": "Denis Gurianov",
            "TOI": 1.95,
            "points": 0.0,
            "iCF": 2.0,
            "iSCF": 1.0,
            "iHDCF": 1.0
        },
        {
            "name": "Jamie Benn",
            "TOI": 5.6,
            "points": 1.0,
            "iCF": 1.0,
            "iSCF": 1.0,
            "iHDCF": 1.0
        },
        {
            "name": "Jason Robertson",
            "TOI": 6.0166666666667,
            "points": 1.0,
            "iCF": 2.0,
            "iSCF": 1.0,
            "iHDCF": 0.0
        },
        {
            "name": "Joe Pavelski",
            "TOI": 5.6,
            "points": 0.0,
            "iCF": 2.0,
            "iSCF": 1.0,
            "iHDCF": 0.0
        },
        {
            "name": "Mason Marchment",
            "TOI": 2.2333333333333,
            "points": 0.0,
            "iCF": 1.0,
            "iSCF": 1.0,
            "iHDCF": 0.0
        },
        {
            "name": "Miro Heiskanen",
            "TOI": 5.9,
            "points": 1.0,
            "iCF": 3.0,
            "iSCF": 2.0,
            "iHDCF": 0.0
        },
        {
            "name": "Radek Faksa",
            "TOI": 0.38333333333333,
            "points": 0.0,
            "iCF": 0.0,
            "iSCF": 0.0,
            "iHDCF": 0.0
        },
        {
            "name": "Ryan Suter",
            "TOI": 2.0166666666667,
            "points": 0.0,
            "iCF": 1.0,
            "iSCF": 1.0,
            "iHDCF": 0.0
        },
        {
            "name": "Tyler Seguin",
            "TOI": 5.8833333333333,
            "points": 0.0,
            "iCF": 1.0,
            "iSCF": 1.0,
            "iHDCF": 0.0
        },
        {
            "name": "Wyatt Johnston",
            "TOI": 1.8666666666667,
            "points": 0.0,
            "iCF": 1.0,
            "iSCF": 1.0,
            "iHDCF": 0.0
        }
    ]
}